pump_offline_calibration_plugin/__init__.py
pump_offline_calibration_plugin/pump_offline_calibration.py
pump_offline_calibration_plugin/test_pump_offline_calibration.py
pump_offline_calibration_plugin/ui/contrib/jobs/pump_offline_calibration_plugin.yaml
pump_offline_calibration_plugin-1.0.2.dist-info/LICENSE.txt
pump_offline_calibration_plugin-1.0.2.dist-info/METADATA
pump_offline_calibration_plugin-1.0.2.dist-info/WHEEL
pump_offline_calibration_plugin-1.0.2.dist-info/entry_points.txt
pump_offline_calibration_plugin-1.0.2.dist-info/top_level.txt
pump_offline_calibration_plugin-1.0.2.dist-info/RECORD
