Metadata-Version: 2.1
Name: pump-offline-calibration-plugin
Version: 1.0.2
Summary: Perform an offline calibration of pumps.
Home-page: https://github.com/odcambc/pump_offline_calibration_plugin
Author: Chris Macdonald
Author-email: christian.macdonald@ucsf.edu
License: MIT
License-File: LICENSE.txt
